keeshond/__init__.py
keeshond/file_hash_check.py
keeshond/format_dict.py
keeshond/kbpmn/__init__.py
keeshond/kbpmn/kbpmn.py
keeshond/ktoga/__init__.py
keeshond/ktoga/keystore/__init__.py
keeshond/ktoga/keystore/auth.py
keeshond/ktoga/keystore/database.py
keeshond/ktoga/toga_layout/__init__.py
keeshond/ktoga/toga_layout/layout.py
keeshond/ktoga/toga_layout/utils.py
keeshond/ktoml/__init__.py
keeshond/ktoml/toml_validator.py
keeshond/log_analyze_object.py
keeshond/logging_logger.py
keeshond-0.0.5.dist-info/LICENSE
keeshond-0.0.5.dist-info/METADATA
keeshond-0.0.5.dist-info/WHEEL
keeshond-0.0.5.dist-info/RECORD
