Metadata-Version: 2.3
Name: keeshond
Version: 0.0.5
Summary: 
Author: Mel
Author-email: melchior.im.dreital@model-enact-analyze-manage.de
Requires-Python: >=3.11
Classifier: Programming Language :: Python :: 3
Classifier: Programming Language :: Python :: 3.11
Classifier: Programming Language :: Python :: 3.12
Classifier: Programming Language :: Python :: 3.13
Requires-Dist: bcrypt (==3.2.2)
Requires-Dist: ipython (>=9.7.0,<10.0.0)
Requires-Dist: ipywidgets (>=8.1.8,<9.0.0)
Requires-Dist: python-for-android (>=2024.1.21,<2025.0.0)
Requires-Dist: pyyaml (>=6.0.2,<7.0.0)
Requires-Dist: toga-android (>=0.4.8,<0.5.0)
Requires-Dist: toga-core (>=0.4.8,<0.5.0)
Requires-Dist: tomli (>=2.0.1,<3.0.0)
Requires-Dist: werkzeug (>=3.1.3,<4.0.0)
Requires-Dist: xmltodict (>=0.14.2,<0.15.0)
Project-URL: Homepage, https://gitlab.com/pynpakken/keeshond
